GiftsEliza/__init__.py
GiftsEliza/gifts.py
GiftsEliza-0.1.dist-info/METADATA
GiftsEliza-0.1.dist-info/WHEEL
GiftsEliza-0.1.dist-info/top_level.txt
GiftsEliza-0.1.dist-info/RECORD
