Metadata-Version: 2.1
Name: GiftsEliza
Version: 0.1
Summary: simple app module that calcualtes the gifts that the guests bring
Home-page: UNKNOWN
Author: Eliza Karki
Author-email: karkie1@nku.edu
License: UNKNOWN
Platform: UNKNOWN
